{
  "1": ["ethereum", "eth", "mainnet", "ethereum-mainnet", "eth-mainnet", "eth1", "mainnet-eth"],
  "5": ["goerli", "testnet-goerli", "goerli-testnet", "goerli-eth"],
  "7": ["thaichain", "thai-chain", "thai"],
  "10": ["optimism", "op", "optimistic-ethereum", "optimism-mainnet", "optimism-eth", "op-mainnet", "oeth"],
  "11": ["metadium-mainnet", "metadium", "meta-mainnet"],
  "12": ["metadium-testnet", "meta-testnet", "metadium-test"],
  "14": ["flare-mainnet", "flare", "flr"],
  "15": ["diode-prenet", "diode"],
  "16": ["coston", "coston-testnet", "flare-coston"],
  "19": ["songbird", "sgb", "canary-network", "flare-songbird"],
  "20": ["elastos", "elastos-mainnet", "ela-eth"],
  "24": ["kardiachain", "kai", "kardia"],
  "25": ["cronos", "cronos-mainnet", "cro", "crypto-org"],
  "29": ["genesis", "genesis-l1"],
  "42": ["kovan", "kovan-testnet", "kovan-eth"],
  "56": ["binance", "bsc", "bnb", "binancesmartchain", "bsc-mainnet", "bnb-chain", "binance-smart-chain"],
  "97": ["bsc-testnet", "binance-testnet", "bnb-testnet", "chapel"],
  "100": ["gnosis", "gno", "xdai", "gnosis-chain", "gnosis-mainnet", "xdai-chain", "dai-chain"],
  "137": ["polygon", "matic", "polygon-mainnet", "plg", "polygon-pos", "polygon-matic"],
  "250": ["fantom", "ftm", "fantom-mainnet", "fantom-opera", "opera"],
  "324": ["zksync", "zksync-era", "era", "zksync-mainnet", "zkera"],
  "1101": ["polygon-zkevm", "zkevm", "polygon-zk", "zkevm-polygon", "polyzk"],
  "5000": ["mantle", "mantle-mainnet", "mnt"],
  "8453": ["base", "base-mainnet", "coinbase-l2", "base-eth", "bsae"],
  "42161": ["arbitrum", "arb", "arbitrum-one", "arbitrum-mainnet", "arbitrum-eth", "arb-one"],
  "43114": ["avalanche", "avax", "avalanche-mainnet", "avalanche-c-chain", "avax-c-chain", "avax-c"],
  "59144": ["linea", "linea-mainnet", "line"],
  "60808": ["bob", "bob-mainnet", "bobchain"],
  "81457": ["blast", "blast-mainnet", "blast-eth", "blast-l2"],
  "534352": ["scroll", "scroll-mainnet", "scroll-l2"],
  "1313161554": ["aurora", "aurora-mainnet", "aurora-near", "near-aurora"],
  "4457845": ["zero-sepolia", "zerosepolia", "sepolia-zero", "zero-testnet"],
  "7777777": ["zora", "zora-mainnet", "zora-network"],
  "11155111": ["sepolia", "sepolia-testnet", "sepolia-eth"],
  "543210": ["zero", "zero-mainnet", "zero-l2"]
}
